__init__.py
ptpnbound.py
net/Arc.py
net/PTPN.py
net/Place.py
net/Transition.py
net/__init__.py
solver/CPLEX_LPsolver.py
solver/LPsolver.py
solver/ParamsExtractor.py
solver/__init__.py
PTPNperfbound-0.0.1.dist-info/LICENSE
PTPNperfbound-0.0.1.dist-info/METADATA
PTPNperfbound-0.0.1.dist-info/WHEEL
PTPNperfbound-0.0.1.dist-info/entry_points.txt
PTPNperfbound-0.0.1.dist-info/top_level.txt
PTPNperfbound-0.0.1.dist-info/RECORD
